{
    "class": "spikeforest.load_extractors.MdaRecordingExtractorV2.MdaRecordingExtractorV2.MdaRecordingExtractorV2",
    "module": "spikeforest",
    "version": "0.12.7",
    "kwargs": {
        "raw_path": "C:\\Users\\kirca_t5ih59c\\.kachery-cloud\\sha1\\12\\5a\\c8\\125ac8f3fa880d6fa26e597a6a32a31d51fe4701",
        "params": {
            "samplerate": 20000,
            "scale_factor": 0.305176,
            "spike_sign": -1
        },
        "geom": [
            [
                0.0,
                0.0
            ],
            [
                0.0,
                25.0
            ],
            [
                0.0,
                50.0
            ],
            [
                0.0,
                75.0
            ]
        ]
    },
    "annotations": {
        "is_filtered": false,
        "probes_info": [
            {}
        ]
    },
    "properties": {
        "group": [
            0,
            0,
            0,
            0
        ],
        "location": [
            [
                0.0,
                0.0
            ],
            [
                0.0,
                25.0
            ],
            [
                0.0,
                50.0
            ],
            [
                0.0,
                75.0
            ]
        ],
        "gain_to_uV": null,
        "offset_to_uV": null
    },
    "relative_paths": false
}